mega_util/__init__.py
mega_util/direct_dl.py
mega_util/export_dir.py
mega_util/mega_util.py
mega_util-0.1.3.dist-info/METADATA
mega_util-0.1.3.dist-info/RECORD
mega_util-0.1.3.dist-info/WHEEL
mega_util-0.1.3.dist-info/top_level.txt
