Metadata-Version: 2.1
Name: mega-util
Version: 0.1.3
Summary: Python utility library for Mega.nz
Home-page: https://github.com/mycxle/Mega-Util
Author: mycxle
Author-email: mycxle@gmail.com
License: UNKNOWN
Platform: UNKNOWN
Classifier: Programming Language :: Python :: 3
Classifier: License :: OSI Approved :: MIT License
Classifier: Operating System :: OS Independent
